Workbook

Sheet Control Panel
A1: 13-Week Cash Flow Forecast | B1: Value
A2: Company | B2: Pragati Distribution Pvt Ltd
A3: Currency | B3: INR
A4: Forecast Horizon | B4: 13
A5: Minimum Cash Threshold | B5: 1000000
A6: Stress Scenario | B6: Customers pay 20 days late
A8: Refresh instructions
A9: Replace files in data/raw, refresh Power Query, then refresh this workbook.

Sheet Base Forecast
A1: scenario | B1: week_start | C1: opening_cash | D1: receipts | E1: payments | F1: closing_cash | G1: minimum_cash_alert
A2: Base | B2: 2026-01-05 | C2: 1850000.0 | D2: 635000.0 | E2: 300000.0 | F2: 2185000.0 | G2: OK
A3: Base | B3: 2026-01-12 | C3: 2185000.0 | D3: 275000.0 | E3: 65000.0 | F3: 2395000.0 | G3: OK
A4: Base | B4: 2026-01-19 | C4: 2395000.0 | D4: 180000.0 | E4: 125000.0 | F4: 2450000.0 | G4: OK
A5: Base | B5: 2026-01-26 | C5: 2450000.0 | D5: 0 | E5: 320000.0 | F5: 2130000.0 | G5: OK
A6: Base | B6: 2026-02-02 | C6: 2130000.0 | D6: 360000.0 | E6: 185000.0 | F6: 2305000.0 | G6: OK
A7: Base | B7: 2026-02-09 | C7: 2305000.0 | D7: 225000.0 | E7: 165000.0 | F7: 2365000.0 | G7: OK
A8: Base | B8: 2026-02-16 | C8: 2365000.0 | D8: 310000.0 | E8: 140000.0 | F8: 2535000.0 | G8: OK
A9: Base | B9: 2026-02-23 | C9: 2535000.0 | D9: 80000.0 | E9: 0 | F9: 2615000.0 | G9: OK
A10: Base | B10: 2026-03-02 | C10: 2615000.0 | D10: 190000.0 | E10: 0 | F10: 2805000.0 | G10: OK
A11: Base | B11: 2026-03-09 | C11: 2805000.0 | D11: 145000.0 | E11: 0 | F11: 2950000.0 | G11: OK
A12: Base | B12: 2026-03-16 | C12: 2950000.0 | D12: 0 | E12: 0 | F12: 2950000.0 | G12: OK
... A14: Base | B14: 2026-03-30 | C14: 2950000.0 | D14: 0 | E14: 0 | F14: 2950000.0 | G14: OK

Sheet Stress Forecast
A1: scenario | B1: week_start | C1: opening_cash | D1: receipts | E1: payments | F1: closing_cash | G1: minimum_cash_alert
A2: Customer_Payments_20_Days_Late | B2: 2026-01-05 | C2: 1850000.0 | D2: 215000.0 | E2: 300000.0 | F2: 1765000.0 | G2: OK
A3: Customer_Payments_20_Days_Late | B3: 2026-01-12 | C3: 1765000.0 | D3: 275000.0 | E3: 65000.0 | F3: 1975000.0 | G3: OK
A4: Customer_Payments_20_Days_Late | B4: 2026-01-19 | C4: 1975000.0 | D4: 0 | E4: 125000.0 | F4: 1850000.0 | G4: OK
A5: Customer_Payments_20_Days_Late | B5: 2026-01-26 | C5: 1850000.0 | D5: 420000.0 | E5: 320000.0 | F5: 1950000.0 | G5: OK
A6: Customer_Payments_20_Days_Late | B6: 2026-02-02 | C6: 1950000.0 | D6: 0 | E6: 185000.0 | F6: 1765000.0 | G6: OK
A7: Customer_Payments_20_Days_Late | B7: 2026-02-09 | C7: 1765000.0 | D7: 180000.0 | E7: 165000.0 | F7: 1780000.0 | G7: OK
A8: Customer_Payments_20_Days_Late | B8: 2026-02-16 | C8: 1780000.0 | D8: 0 | E8: 140000.0 | F8: 1640000.0 | G8: OK
A9: Customer_Payments_20_Days_Late | B9: 2026-02-23 | C9: 1640000.0 | D9: 440000.0 | E9: 0 | F9: 2080000.0 | G9: OK
A10: Customer_Payments_20_Days_Late | B10: 2026-03-02 | C10: 2080000.0 | D10: 225000.0 | E10: 0 | F10: 2305000.0 | G10: OK
A11: Customer_Payments_20_Days_Late | B11: 2026-03-09 | C11: 2305000.0 | D11: 310000.0 | E11: 0 | F11: 2615000.0 | G11: OK
A12: Customer_Payments_20_Days_Late | B12: 2026-03-16 | C12: 2615000.0 | D12: 0 | E12: 0 | F12: 2615000.0 | G12: OK
... A14: Customer_Payments_20_Days_Late | B14: 2026-03-30 | C14: 2805000.0 | D14: 145000.0 | E14: 0 | F14: 2950000.0 | G14: OK

Sheet Raw Invoices
A1: invoice_id | B1: customer | C1: invoice_date | D1: due_date | E1: amount | F1: expected_payment_date | G1: actual_payment_date | H1: payment_status
A2: INV-1001 | B2: Acme Retail | C2: 2025-11-15 | D2: 2026-01-08 | E2: 420000 | F2: 2026-01-08 | H2: Open
A3: INV-1002 | B3: Beacon Foods | C3: 2025-12-01 | D3: 2026-01-15 | E3: 275000 | F3: 2026-01-15 | G3: 2026-01-12 | H3: Paid
A4: INV-1003 | B4: CityMart | C4: 2025-12-10 | D4: 2026-01-22 | E4: 180000 | F4: 2026-01-22 | H4: Open
A5: INV-1004 | B5: Delta Health | C5: 2025-12-18 | D5: 2026-02-05 | E5: 360000 | F5: 2026-02-05 | H5: Open
A6: INV-1005 | B6: Evergreen Hotels | C6: 2025-12-22 | D6: 2026-02-12 | E6: 225000 | F6: 2026-02-12 | H6: Open
A7: INV-1006 | B7: Acme Retail | C7: 2026-01-02 | D7: 2026-02-19 | E7: 310000 | F7: 2026-02-19 | H7: Open
A8: INV-1007 | B8: Beacon Foods | C8: 2026-01-03 | D8: 2026-03-05 | E8: 190000 | F8: 2026-03-05 | H8: Open
A9: INV-1008 | B9: CityMart | C9: 2026-01-04 | D9: 2026-03-12 | E9: 145000 | F9: 2026-03-12 | H9: Open
A10: INV-1009 | B10: Delta Health | C10: 2025-12-01 | D10: 2025-12-20 | E10: 95000 | F10: 2025-12-20 | H10: Overdue

Sheet Raw Supplier Payments
A1: payment_id | B1: vendor | C1: payment_category | D1: payment_date | E1: amount | F1: payment_status
A2: PAY-2001 | B2: Northstar Materials | C2: Inventory | D2: 2026-01-09 | E2: 210000 | F2: Planned
A3: PAY-2002 | B3: OfficeHub | C3: Operating Expense | D3: 2026-01-16 | E3: 65000 | F3: Planned
A4: PAY-2003 | B4: LogiMove | C4: Distribution | D4: 2026-01-23 | E4: 125000 | F4: Planned
A5: PAY-2004 | B5: Northstar Materials | C5: Inventory | D5: 2026-02-06 | E5: 185000 | F5: Planned
A6: PAY-2005 | B6: CloudServe | C6: Operating Expense | D6: 2026-02-13 | E6: 55000 | F6: Planned
A7: PAY-2006 | B7: LogiMove | C7: Distribution | D7: 2026-02-20 | E7: 140000 | F7: Planned

Sheet Raw Other Cash Flows
A1: cash_flow_id | B1: flow_type | C1: category | D1: flow_date | E1: amount | F1: description
A2: CF-0001 | B2: Receipt | C2: Other Receipts | D2: 2026-01-05 | E2: 120000 | F2: Opening-week miscellaneous receipts
A3: CF-0002 | B3: Payment | C3: Operating Expense | D3: 2026-01-05 | E3: 90000 | F3: Opening-week operating expense
A4: CF-0003 | B4: Payment | C4: Payroll | D4: 2026-01-30 | E4: 320000 | F4: Monthly payroll
A5: CF-0004 | B5: Payment | C5: Tax | D5: 2026-02-10 | E5: 110000 | F5: Advance tax payment
A6: CF-0005 | B6: Receipt | C6: Other Receipts | D6: 2026-02-27 | E6: 80000 | F6: Insurance reimbursement

Sheet Raw Configuration
A1: config_key | B1: config_value
A2: company_name | B2: Pragati Distribution Pvt Ltd
A3: as_of_date | B3: 2026-01-05
A4: horizon_weeks | B4: 13
A5: minimum_cash_threshold | B5: 1000000
A6: stress_delay_days | B6: 20
A7: currency | B7: INR

Sheet Raw Opening Cash
A1: as_of_date | B1: opening_cash
A2: 2026-01-05 | B2: 1850000

Sheet Scenario Comparison
A1: Week Start | B1: Base Closing Cash | C1: Stress Closing Cash | D1: Stress Cash Gap | E1: Base Alert | F1: Stress Alert
A2: 2026-01-05 | B2: ='Base Forecast'!F2 | C2: ='Stress Forecast'!F2 | D2: =B2-C2 | E2: ='Base Forecast'!G2 | F2: ='Stress Forecast'!G2
A3: 2026-01-12 | B3: ='Base Forecast'!F3 | C3: ='Stress Forecast'!F3 | D3: =B3-C3 | E3: ='Base Forecast'!G3 | F3: ='Stress Forecast'!G3
A4: 2026-01-19 | B4: ='Base Forecast'!F4 | C4: ='Stress Forecast'!F4 | D4: =B4-C4 | E4: ='Base Forecast'!G4 | F4: ='Stress Forecast'!G4
A5: 2026-01-26 | B5: ='Base Forecast'!F5 | C5: ='Stress Forecast'!F5 | D5: =B5-C5 | E5: ='Base Forecast'!G5 | F5: ='Stress Forecast'!G5
A6: 2026-02-02 | B6: ='Base Forecast'!F6 | C6: ='Stress Forecast'!F6 | D6: =B6-C6 | E6: ='Base Forecast'!G6 | F6: ='Stress Forecast'!G6
A7: 2026-02-09 | B7: ='Base Forecast'!F7 | C7: ='Stress Forecast'!F7 | D7: =B7-C7 | E7: ='Base Forecast'!G7 | F7: ='Stress Forecast'!G7
A8: 2026-02-16 | B8: ='Base Forecast'!F8 | C8: ='Stress Forecast'!F8 | D8: =B8-C8 | E8: ='Base Forecast'!G8 | F8: ='Stress Forecast'!G8
A9: 2026-02-23 | B9: ='Base Forecast'!F9 | C9: ='Stress Forecast'!F9 | D9: =B9-C9 | E9: ='Base Forecast'!G9 | F9: ='Stress Forecast'!G9
A10: 2026-03-02 | B10: ='Base Forecast'!F10 | C10: ='Stress Forecast'!F10 | D10: =B10-C10 | E10: ='Base Forecast'!G10 | F10: ='Stress Forecast'!G10
A11: 2026-03-09 | B11: ='Base Forecast'!F11 | C11: ='Stress Forecast'!F11 | D11: =B11-C11 | E11: ='Base Forecast'!G11 | F11: ='Stress Forecast'!G11
A12: 2026-03-16 | B12: ='Base Forecast'!F12 | C12: ='Stress Forecast'!F12 | D12: =B12-C12 | E12: ='Base Forecast'!G12 | F12: ='Stress Forecast'!G12
A13: 2026-03-23 | B13: ='Base Forecast'!F13 | C13: ='Stress Forecast'!F13 | D13: =B13-C13 | E13: ='Base Forecast'!G13 | F13: ='Stress Forecast'!G13
A14: 2026-03-30 | B14: ='Base Forecast'!F14 | C14: ='Stress Forecast'!F14 | D14: =B14-C14 | E14: ='Base Forecast'!G14 | F14: ='Stress Forecast'!G14

Sheet Receipts
A1: week_start | B1: customer_receipts
A2: 2026-01-05 | B2: 635000.0
A3: 2026-01-12 | B3: 275000.0
A4: 2026-01-19 | B4: 180000.0
A5: 2026-01-26 | B5: 0
A6: 2026-02-02 | B6: 360000.0
A7: 2026-02-09 | B7: 225000.0
A8: 2026-02-16 | B8: 310000.0
A9: 2026-02-23 | B9: 80000.0
A10: 2026-03-02 | B10: 190000.0
A11: 2026-03-09 | B11: 145000.0
A12: 2026-03-16 | B12: 0
... A14: 2026-03-30 | B14: 0

Sheet Payments
A1: week_start | B1: supplier_and_other_payments
A2: 2026-01-05 | B2: 300000.0
A3: 2026-01-12 | B3: 65000.0
A4: 2026-01-19 | B4: 125000.0
A5: 2026-01-26 | B5: 320000.0
A6: 2026-02-02 | B6: 185000.0
A7: 2026-02-09 | B7: 165000.0
A8: 2026-02-16 | B8: 140000.0
A9: 2026-02-23 | B9: 0
A10: 2026-03-02 | B10: 0
A11: 2026-03-09 | B11: 0
A12: 2026-03-16 | B12: 0
... A14: 2026-03-30 | B14: 0

Sheet Data Quality
A1: Check | B1: Result
A2: Base forecast weeks | B2: 13
A3: Stress forecast weeks | B3: 13
A4: Scenario week counts match | B4: PASS
A5: Base closing cash values present | B5: PASS
A6: Stress closing cash values present | B6: PASS
